<?xml version="1.0" encoding="UTF-8"?>
<mxfile host="app.diagrams.net" agent="Mozilla/5.0 (Windows NT 10.0; Win64; x64) AppleWebKit/537.36 (KHTML, like Gecko) Chrome/129.0.0.0 Safari/537.36" version="24.7.17">
  <diagram name="Page-1" id="kYdlWCcFRPNSPKTtEJFJ">
    <mxGraphModel dx="2924" dy="1132" grid="1" gridSize="10" guides="1" tooltips="1" connect="1" arrows="1" fold="1" page="1" pageScale="1" pageWidth="850" pageHeight="1100" math="0" shadow="0">
      <root>
        <mxCell id="0" />
        <mxCell id="1" parent="0" />
        <mxCell id="6z9sBZm0ucea2zdIxm34-72" value="" style="rounded=0;whiteSpace=wrap;html=1;" parent="1" vertex="1">
          <mxGeometry x="890" y="460" width="120" height="110" as="geometry" />
        </mxCell>
        <mxCell id="6z9sBZm0ucea2zdIxm34-73" value="" style="rounded=0;whiteSpace=wrap;html=1;" parent="1" vertex="1">
          <mxGeometry x="275" y="810" width="130" height="80" as="geometry" />
        </mxCell>
        <mxCell id="6z9sBZm0ucea2zdIxm34-74" value="" style="rounded=0;whiteSpace=wrap;html=1;" parent="1" vertex="1">
          <mxGeometry x="550" y="670" width="150" height="125" as="geometry" />
        </mxCell>
        <mxCell id="6z9sBZm0ucea2zdIxm34-75" value="" style="rounded=0;whiteSpace=wrap;html=1;" parent="1" vertex="1">
          <mxGeometry x="610" y="80" width="130" height="120" as="geometry" />
        </mxCell>
        <mxCell id="6z9sBZm0ucea2zdIxm34-76" value="" style="rounded=0;whiteSpace=wrap;html=1;" parent="1" vertex="1">
          <mxGeometry x="50" y="600" width="130" height="100" as="geometry" />
        </mxCell>
        <mxCell id="6z9sBZm0ucea2zdIxm34-71" value="" style="rounded=0;whiteSpace=wrap;html=1;" parent="1" vertex="1">
          <mxGeometry x="-130" y="180" width="120" height="90" as="geometry" />
        </mxCell>
        <mxCell id="6z9sBZm0ucea2zdIxm34-46" style="edgeStyle=orthogonalEdgeStyle;rounded=0;orthogonalLoop=1;jettySize=auto;html=1;exitX=0.5;exitY=1;exitDx=0;exitDy=0;entryX=0.5;entryY=0;entryDx=0;entryDy=0;" parent="1" source="6z9sBZm0ucea2zdIxm34-15" target="6z9sBZm0ucea2zdIxm34-18" edge="1">
          <mxGeometry relative="1" as="geometry" />
        </mxCell>
        <mxCell id="6z9sBZm0ucea2zdIxm34-47" style="edgeStyle=orthogonalEdgeStyle;rounded=0;orthogonalLoop=1;jettySize=auto;html=1;exitX=1;exitY=0.5;exitDx=0;exitDy=0;entryX=0.5;entryY=0;entryDx=0;entryDy=0;" parent="1" source="6z9sBZm0ucea2zdIxm34-15" target="6z9sBZm0ucea2zdIxm34-23" edge="1">
          <mxGeometry relative="1" as="geometry" />
        </mxCell>
        <mxCell id="6z9sBZm0ucea2zdIxm34-48" style="edgeStyle=orthogonalEdgeStyle;rounded=0;orthogonalLoop=1;jettySize=auto;html=1;exitX=0;exitY=0.5;exitDx=0;exitDy=0;entryX=0.5;entryY=0;entryDx=0;entryDy=0;" parent="1" source="6z9sBZm0ucea2zdIxm34-15" target="6z9sBZm0ucea2zdIxm34-41" edge="1">
          <mxGeometry relative="1" as="geometry" />
        </mxCell>
        <mxCell id="6z9sBZm0ucea2zdIxm34-15" value="" style="rounded=0;whiteSpace=wrap;html=1;" parent="1" vertex="1">
          <mxGeometry x="350" y="320" width="120" height="60" as="geometry" />
        </mxCell>
        <mxCell id="6z9sBZm0ucea2zdIxm34-17" value="proovipartii" style="text;html=1;align=center;verticalAlign=middle;whiteSpace=wrap;rounded=0;" parent="1" vertex="1">
          <mxGeometry x="380" y="335" width="60" height="30" as="geometry" />
        </mxCell>
        <mxCell id="6z9sBZm0ucea2zdIxm34-49" style="edgeStyle=orthogonalEdgeStyle;rounded=0;orthogonalLoop=1;jettySize=auto;html=1;exitX=0.5;exitY=1;exitDx=0;exitDy=0;entryX=0.5;entryY=0;entryDx=0;entryDy=0;" parent="1" source="6z9sBZm0ucea2zdIxm34-18" target="6z9sBZm0ucea2zdIxm34-21" edge="1">
          <mxGeometry relative="1" as="geometry">
            <Array as="points">
              <mxPoint x="410" y="610" />
              <mxPoint x="340" y="610" />
            </Array>
          </mxGeometry>
        </mxCell>
        <mxCell id="6z9sBZm0ucea2zdIxm34-80" style="edgeStyle=orthogonalEdgeStyle;rounded=0;orthogonalLoop=1;jettySize=auto;html=1;exitX=0.5;exitY=1;exitDx=0;exitDy=0;entryX=0.5;entryY=0;entryDx=0;entryDy=0;" parent="1" source="6z9sBZm0ucea2zdIxm34-18" target="6z9sBZm0ucea2zdIxm34-74" edge="1">
          <mxGeometry relative="1" as="geometry" />
        </mxCell>
        <mxCell id="6z9sBZm0ucea2zdIxm34-18" value="" style="rounded=0;whiteSpace=wrap;html=1;" parent="1" vertex="1">
          <mxGeometry x="350" y="490" width="120" height="60" as="geometry" />
        </mxCell>
        <mxCell id="6z9sBZm0ucea2zdIxm34-19" value="maismliste logi" style="text;html=1;align=center;verticalAlign=middle;whiteSpace=wrap;rounded=0;" parent="1" vertex="1">
          <mxGeometry x="380" y="505" width="60" height="30" as="geometry" />
        </mxCell>
        <mxCell id="6z9sBZm0ucea2zdIxm34-81" style="edgeStyle=orthogonalEdgeStyle;rounded=0;orthogonalLoop=1;jettySize=auto;html=1;exitX=0.5;exitY=1;exitDx=0;exitDy=0;entryX=0.5;entryY=0;entryDx=0;entryDy=0;" parent="1" source="6z9sBZm0ucea2zdIxm34-21" target="6z9sBZm0ucea2zdIxm34-73" edge="1">
          <mxGeometry relative="1" as="geometry" />
        </mxCell>
        <mxCell id="6z9sBZm0ucea2zdIxm34-21" value="" style="rounded=0;whiteSpace=wrap;html=1;" parent="1" vertex="1">
          <mxGeometry x="280" y="670" width="120" height="60" as="geometry" />
        </mxCell>
        <mxCell id="6z9sBZm0ucea2zdIxm34-22" value="kasutaja" style="text;html=1;align=center;verticalAlign=middle;whiteSpace=wrap;rounded=0;" parent="1" vertex="1">
          <mxGeometry x="310" y="685" width="60" height="30" as="geometry" />
        </mxCell>
        <mxCell id="6z9sBZm0ucea2zdIxm34-79" style="edgeStyle=orthogonalEdgeStyle;rounded=0;orthogonalLoop=1;jettySize=auto;html=1;exitX=1;exitY=0.5;exitDx=0;exitDy=0;entryX=0;entryY=0.5;entryDx=0;entryDy=0;" parent="1" source="6z9sBZm0ucea2zdIxm34-23" target="6z9sBZm0ucea2zdIxm34-69" edge="1">
          <mxGeometry relative="1" as="geometry" />
        </mxCell>
        <mxCell id="6z9sBZm0ucea2zdIxm34-23" value="" style="rounded=0;whiteSpace=wrap;html=1;" parent="1" vertex="1">
          <mxGeometry x="590" y="490" width="110" height="60" as="geometry" />
        </mxCell>
        <mxCell id="6z9sBZm0ucea2zdIxm34-24" value="kostisosa" style="text;html=1;align=center;verticalAlign=middle;whiteSpace=wrap;rounded=0;" parent="1" vertex="1">
          <mxGeometry x="620" y="505" width="60" height="30" as="geometry" />
        </mxCell>
        <mxCell id="6z9sBZm0ucea2zdIxm34-51" style="edgeStyle=orthogonalEdgeStyle;rounded=0;orthogonalLoop=1;jettySize=auto;html=1;exitX=1;exitY=0.5;exitDx=0;exitDy=0;entryX=0.5;entryY=0;entryDx=0;entryDy=0;" parent="1" source="6z9sBZm0ucea2zdIxm34-25" target="6z9sBZm0ucea2zdIxm34-15" edge="1">
          <mxGeometry relative="1" as="geometry" />
        </mxCell>
        <mxCell id="6z9sBZm0ucea2zdIxm34-77" style="edgeStyle=orthogonalEdgeStyle;rounded=0;orthogonalLoop=1;jettySize=auto;html=1;exitX=0;exitY=0.5;exitDx=0;exitDy=0;entryX=1;entryY=0.5;entryDx=0;entryDy=0;" parent="1" source="6z9sBZm0ucea2zdIxm34-25" target="6z9sBZm0ucea2zdIxm34-71" edge="1">
          <mxGeometry relative="1" as="geometry" />
        </mxCell>
        <mxCell id="6z9sBZm0ucea2zdIxm34-25" value="" style="rounded=0;whiteSpace=wrap;html=1;" parent="1" vertex="1">
          <mxGeometry x="90" y="150" width="120" height="60" as="geometry" />
        </mxCell>
        <mxCell id="6z9sBZm0ucea2zdIxm34-26" value="ollesort" style="text;html=1;align=center;verticalAlign=middle;whiteSpace=wrap;rounded=0;" parent="1" vertex="1">
          <mxGeometry x="120" y="165" width="60" height="30" as="geometry" />
        </mxCell>
        <mxCell id="6z9sBZm0ucea2zdIxm34-82" style="edgeStyle=orthogonalEdgeStyle;rounded=0;orthogonalLoop=1;jettySize=auto;html=1;exitX=0;exitY=0.5;exitDx=0;exitDy=0;entryX=0.5;entryY=0;entryDx=0;entryDy=0;" parent="1" source="6z9sBZm0ucea2zdIxm34-41" target="6z9sBZm0ucea2zdIxm34-76" edge="1">
          <mxGeometry relative="1" as="geometry" />
        </mxCell>
        <mxCell id="6z9sBZm0ucea2zdIxm34-41" value="" style="rounded=0;whiteSpace=wrap;html=1;" parent="1" vertex="1">
          <mxGeometry x="150" y="490" width="120" height="60" as="geometry" />
        </mxCell>
        <mxCell id="6z9sBZm0ucea2zdIxm34-50" style="edgeStyle=orthogonalEdgeStyle;rounded=0;orthogonalLoop=1;jettySize=auto;html=1;" parent="1" source="6z9sBZm0ucea2zdIxm34-42" edge="1">
          <mxGeometry relative="1" as="geometry">
            <mxPoint x="340" y="670" as="targetPoint" />
            <Array as="points">
              <mxPoint x="210" y="610" />
              <mxPoint x="341" y="610" />
            </Array>
          </mxGeometry>
        </mxCell>
        <mxCell id="6z9sBZm0ucea2zdIxm34-42" value="logikand" style="text;html=1;align=center;verticalAlign=middle;whiteSpace=wrap;rounded=0;" parent="1" vertex="1">
          <mxGeometry x="180" y="505" width="60" height="30" as="geometry" />
        </mxCell>
        <mxCell id="6z9sBZm0ucea2zdIxm34-65" value="&lt;div&gt;ID: int&lt;/div&gt;&lt;div&gt;Nimi: string&lt;/div&gt;&lt;div&gt;Kirjeldus: string&lt;/div&gt;&lt;div&gt;Seosed 1*&lt;/div&gt;&lt;div&gt;&lt;br&gt;&lt;/div&gt;&lt;div&gt;&lt;br&gt;&lt;/div&gt;" style="text;html=1;align=center;verticalAlign=middle;whiteSpace=wrap;rounded=0;" parent="1" vertex="1">
          <mxGeometry x="-140" y="220" width="140" height="30" as="geometry" />
        </mxCell>
        <mxCell id="6z9sBZm0ucea2zdIxm34-66" value="&lt;div&gt;Partii: Proovipartii (seos)&lt;/div&gt;&lt;div&gt;Kuupäev: date&lt;/div&gt;&lt;div&gt;Kirjeldus: string&lt;/div&gt;&lt;div&gt;Kasutaja: Kasutaja (seos)&lt;/div&gt;&lt;div&gt;&lt;br&gt;&lt;/div&gt;" style="text;html=1;align=center;verticalAlign=middle;whiteSpace=wrap;rounded=0;" parent="1" vertex="1">
          <mxGeometry x="60" y="640" width="110" height="30" as="geometry" />
        </mxCell>
        <mxCell id="6z9sBZm0ucea2zdIxm34-67" value="&lt;div&gt;ID: int&lt;/div&gt;&lt;div&gt;Nimi: string&lt;/div&gt;&lt;div&gt;Kasutajanimi: string&lt;/div&gt;&lt;div&gt;Parool: string&lt;/div&gt;" style="text;html=1;align=center;verticalAlign=middle;whiteSpace=wrap;rounded=0;" parent="1" vertex="1">
          <mxGeometry x="260" y="835" width="160" height="30" as="geometry" />
        </mxCell>
        <mxCell id="6z9sBZm0ucea2zdIxm34-68" value="ID: int&#xa;Partii: Proovipartii (seos)&#xa;Kuupäev: date&#xa;Kasutaja: Kasutaja (seos)&#xa;Hinnd: int&#xa;Selgitus: string" style="text;html=1;align=center;verticalAlign=middle;whiteSpace=wrap;rounded=0;" parent="1" vertex="1">
          <mxGeometry x="550" y="717.5" width="150" height="30" as="geometry" />
        </mxCell>
        <mxCell id="6z9sBZm0ucea2zdIxm34-69" value="&lt;div&gt;Nimetus: string&lt;/div&gt;&lt;div&gt;Ühik: string&lt;/div&gt;&lt;div&gt;Ühikuhind: float&lt;/div&gt;&lt;div&gt;Kogus pruulimisel: float&lt;/div&gt;&lt;div&gt;Summa: float&lt;/div&gt;&lt;div&gt;&lt;br&gt;&lt;/div&gt;" style="text;html=1;align=center;verticalAlign=middle;whiteSpace=wrap;rounded=0;" parent="1" vertex="1">
          <mxGeometry x="890" y="510" width="120" height="20" as="geometry" />
        </mxCell>
        <mxCell id="6z9sBZm0ucea2zdIxm34-70" value="&lt;div&gt;ID: int&lt;/div&gt;&lt;div&gt;Õllesort: Õllesort (seos)&lt;/div&gt;&lt;div&gt;Partii kuupäev: date&lt;/div&gt;&lt;div&gt;Kood: string&lt;/div&gt;&lt;div&gt;Kirjeldus: string&lt;/div&gt;&lt;div&gt;&lt;br&gt;&lt;/div&gt;&lt;div&gt;&lt;br&gt;&lt;/div&gt;" style="text;html=1;align=center;verticalAlign=middle;whiteSpace=wrap;rounded=0;" parent="1" vertex="1">
          <mxGeometry x="620" y="135" width="110" height="30" as="geometry" />
        </mxCell>
        <mxCell id="6z9sBZm0ucea2zdIxm34-78" style="edgeStyle=orthogonalEdgeStyle;rounded=0;orthogonalLoop=1;jettySize=auto;html=1;exitX=1;exitY=0;exitDx=0;exitDy=0;entryX=-0.008;entryY=0.558;entryDx=0;entryDy=0;entryPerimeter=0;" parent="1" source="6z9sBZm0ucea2zdIxm34-15" target="6z9sBZm0ucea2zdIxm34-75" edge="1">
          <mxGeometry relative="1" as="geometry" />
        </mxCell>
      </root>
    </mxGraphModel>
  </diagram>
</mxfile>
